ivqr_gmm/__init__.py
ivqr_gmm/testing.py
ivqr_gmm-0.1.dist-info/METADATA
ivqr_gmm-0.1.dist-info/RECORD
ivqr_gmm-0.1.dist-info/WHEEL
ivqr_gmm-0.1.dist-info/top_level.txt
